{
  "$schema": "http://json-schema.org/draft-07/schema#",
  "title": "BDS_build_conf",
  "type": "array",
  "items": { "$ref": "#/definitions/base" },
  "definitions": {
    "base": {
      "type": "object",
      "additionalProperties": false,
      "required": ["Taxonomy_id", "Description", "Reference", "PMID", "Species", "Brain_region", "Root_nodes", "non_taxonomy_roots"],
      "properties": {
        "Taxonomy_id" :  {
          "type": "string",
          "description": "Accession for Allen Taxonomy"
        },
        "Description":  {
          "type": "string",
          "description": "Description of Allen Taxonomy"
        },
        "Reference":  {
          "type": "string",
          "description": "Reference to Allen Taxonomy"
        },
        "PMID": {
          "type": "array",
          "items": {
            "type": "string",
            "description": "PMID of reference for analysis."
          }
        },
        "Species": {
          "type": "array",
          "items": {
            "type": "string",
            "description": "Ontology ID (NCBI curie) of species used in analysis."
          }
        },
        "Species_abbv": {
          "type": "array",
          "items": {
            "type": "string",
            "description": "Species abbreviation."
          }
        },
        "Gene_abbv": {
          "type": "array",
          "items": {
            "type": "string",
            "description": "Gene abbreviation."
          }
        },
        "Brain_region": {
          "type": "array",
          "items": {
            "type": "string",
            "description": "Ontology ID (curie) of brain region used in analysis."
          }
        },
        "Brain_region_abbv": {
          "type": "array",
          "items": {
            "type": "string",
            "description": "Brain region abbreviation."
          }
        },
        "Reference_gene_list": {
          "type": "array",
          "items": {
            "type": "string",
            "description": "Reference gene list."
          }
        },
        "Root_nodes": {
          "type": "array",
          "items": {
            "$ref" : "#/definitions/root_node"  }
        },
        "non_taxonomy_roots": {
          "type": "array",
          "items": {
            "$ref" : "#/definitions/non_taxon_root"  }
        }
      }
    },
    "root_node":{
      "type": "object",
      "additionalProperties": false,
      "required": ["Node", "Cell_type", "Location_relation"],
      "properties": {
        "Node": {
          "type": "string",
          "description": "cell_set_accession of a root node"
        },
        "Cell_type": {
          "type": "string",
          "description": "Gross cell type corresponding to root node.  This should not be a term that is already defined as restricted to the location named in Brain_region."
        },
        "Location_relation": {
          "type": "string",
          "description": "The relation to use to link cell type to brain region. See guidance on CL repo.  Rule of thumb: For neurons use has_soma_location. For other cell types use part_of."
        }
      }
    },
    "non_taxon_root":{
      "type": "object",
      "additionalProperties": false,
      "required": ["Node", "Cell_type"],
      "properties": {
        "Node": {
          "type": "string",
          "description": "cell_set_accession of a non-taxonomy root node"
        },
        "Cell_type": {
          "type": "string",
          "description": "Gross cell type corresponding to a non-taxonomy root node."
        }
      }
    }
  }
}
